gen_data/__init__.py
gen_data/generator.py
gen_data-0.1.0.dist-info/METADATA
gen_data-0.1.0.dist-info/WHEEL
gen_data-0.1.0.dist-info/top_level.txt
gen_data-0.1.0.dist-info/RECORD
