Metadata-Version: 2.1
Name: gen-data
Version: 0.1.0
Summary: A tool to generate synthetic data from prompts
Home-page: UNKNOWN
Author: vivek kolasani
Author-email: kolasaniv1996@gmail.com
License: UNKNOWN
Platform: UNKNOWN
Requires-Dist: transformers (>=4.0.0)
Requires-Dist: torch (>=1.7.0)
